myoquant/ATP_analysis.py
myoquant/HE_analysis.py
myoquant/SDH_analysis.py
myoquant/__init__.py
myoquant/__main__.py
myoquant/common_func.py
myoquant/draw_line.py
myoquant/gradcam.py
myoquant/commands/__init__.py
myoquant/commands/docs.py
myoquant/commands/run_atp.py
myoquant/commands/run_he.py
myoquant/commands/run_sdh.py
myoquant/streamlit/Dockerfile
myoquant/streamlit/README.md
myoquant/streamlit/pyproject.toml
myoquant/streamlit/run.py
myoquant/streamlit/pages/ATP_staining.py
myoquant/streamlit/pages/Fluo_staining.py
myoquant/streamlit/pages/HE_staining.py
myoquant/streamlit/pages/SDH_staining.py
myoquant/streamlit/pages/home.py
myoquant-0.4.0.dist-info/METADATA
myoquant-0.4.0.dist-info/WHEEL
myoquant-0.4.0.dist-info/entry_points.txt
myoquant-0.4.0.dist-info/licenses/LICENSE
myoquant-0.4.0.dist-info/RECORD
